instructor/__init__.py
instructor/auto_client.py
instructor/distil.py
instructor/mode.py
instructor/models.py
instructor/templating.py
instructor/_types/__init__.py
instructor/_types/_alias.py
instructor/batch/__init__.py
instructor/batch/models.py
instructor/batch/processor.py
instructor/batch/request.py
instructor/batch/utils.py
instructor/batch/providers/__init__.py
instructor/batch/providers/anthropic.py
instructor/batch/providers/base.py
instructor/batch/providers/openai.py
instructor/cache/__init__.py
instructor/cli/__init__.py
instructor/cli/batch.py
instructor/cli/cli.py
instructor/cli/deprecated_hub.py
instructor/cli/files.py
instructor/cli/jobs.py
instructor/cli/usage.py
instructor/core/__init__.py
instructor/core/client.py
instructor/core/exceptions.py
instructor/core/hooks.py
instructor/core/patch.py
instructor/core/retry.py
instructor/dsl/__init__.py
instructor/dsl/citation.py
instructor/dsl/iterable.py
instructor/dsl/maybe.py
instructor/dsl/parallel.py
instructor/dsl/partial.py
instructor/dsl/simple_type.py
instructor/processing/__init__.py
instructor/processing/function_calls.py
instructor/processing/multimodal.py
instructor/processing/response.py
instructor/processing/schema.py
instructor/processing/validators.py
instructor/providers/README.md
instructor/providers/__init__.py
instructor/providers/anthropic/__init__.py
instructor/providers/anthropic/client.py
instructor/providers/anthropic/utils.py
instructor/providers/bedrock/__init__.py
instructor/providers/bedrock/client.py
instructor/providers/bedrock/utils.py
instructor/providers/cerebras/__init__.py
instructor/providers/cerebras/client.py
instructor/providers/cerebras/utils.py
instructor/providers/cohere/__init__.py
instructor/providers/cohere/client.py
instructor/providers/cohere/utils.py
instructor/providers/fireworks/__init__.py
instructor/providers/fireworks/client.py
instructor/providers/fireworks/utils.py
instructor/providers/gemini/__init__.py
instructor/providers/gemini/client.py
instructor-1.11.0.dist-info/METADATA
instructor-1.11.0.dist-info/WHEEL
instructor-1.11.0.dist-info/entry_points.txt
instructor-1.11.0.dist-info/licenses/LICENSE
instructor-1.11.0.dist-info/RECORD
